trie/__init__.py
trie/binary.py
trie/branches.py
trie/constants.py
trie/exceptions.py
trie/fog.py
trie/hexary.py
trie/iter.py
trie/smt.py
trie/typing.py
trie/validation.py
trie/utils/__init__.py
trie/utils/binaries.py
trie/utils/db.py
trie/utils/nibbles.py
trie/utils/nodes.py
trie-3.0.1.dist-info/LICENSE
trie-3.0.1.dist-info/METADATA
trie-3.0.1.dist-info/WHEEL
trie-3.0.1.dist-info/top_level.txt
trie-3.0.1.dist-info/RECORD
