Metadata-Version: 2.1
Name: trie
Version: 3.0.1
Summary: Python implementation of the Ethereum Trie structure
Home-page: https://github.com/ethereum/py-trie
Author: The Ethereum Foundation
Author-email: snakecharmers@ethereum.org
License: MIT
Keywords: ethereum blockchain evm trie merkle
Classifier: Development Status :: 5 - Production/Stable
Classifier: Intended Audience :: Developers
Classifier: License :: OSI Approved :: MIT License
Classifier: Natural Language :: English
Classifier: Programming Language :: Python :: 3
Classifier: Programming Language :: Python :: 3.8
Classifier: Programming Language :: Python :: 3.9
Classifier: Programming Language :: Python :: 3.10
Classifier: Programming Language :: Python :: 3.11
Classifier: Programming Language :: Python :: 3.12
Requires-Python: >=3.8, <4
License-File: LICENSE
Requires-Dist: eth-hash>=0.1.0
Requires-Dist: eth-utils>=2.0.0
Requires-Dist: hexbytes>=0.2.3
Requires-Dist: rlp>=3
Requires-Dist: sortedcontainers>=2.1.0
Provides-Extra: dev
Requires-Dist: build>=0.9.0; extra == "dev"
Requires-Dist: bumpversion>=0.5.3; extra == "dev"
Requires-Dist: eth-hash<1.0.0,>=0.1.0; extra == "dev"
Requires-Dist: ipython; extra == "dev"
Requires-Dist: pre-commit>=3.4.0; extra == "dev"
Requires-Dist: tox>=4.0.0; extra == "dev"
Requires-Dist: twine; extra == "dev"
Requires-Dist: wheel; extra == "dev"
Requires-Dist: towncrier<22,>=21; extra == "dev"
Requires-Dist: hypothesis<7,>=6.56.4; extra == "dev"
Requires-Dist: pycryptodome; extra == "dev"
Requires-Dist: pytest>=7.0.0; extra == "dev"
Requires-Dist: pytest-xdist>=2.4.0; extra == "dev"
Provides-Extra: docs
Requires-Dist: towncrier<22,>=21; extra == "docs"
Provides-Extra: test
Requires-Dist: hypothesis<7,>=6.56.4; extra == "test"
Requires-Dist: pycryptodome; extra == "test"
Requires-Dist: pytest>=7.0.0; extra == "test"
Requires-Dist: pytest-xdist>=2.4.0; extra == "test"
